tomogui/__init__.py
tomogui/__main__.py
tomogui/_version.py
tomogui/setup.py
tomogui/app/__init__.py
tomogui/app/creator.py
tomogui/app/invert.py
tomogui/app/materials.py
tomogui/app/norm.py
tomogui/app/project.py
tomogui/app/recons.py
tomogui/configuration/__init__.py
tomogui/configuration/config.py
tomogui/core/__init__.py
tomogui/core/setup.py
tomogui/core/utils.py
tomogui/data/__init__.py
tomogui/data/data.py
tomogui/gui/MainWidget.py
tomogui/gui/NewProjectDialog.py
tomogui/gui/ProjectWidget.py
tomogui/gui/__init__.py
tomogui/gui/setup.py
tomogui/gui/creator/AbsMatCreator.py
tomogui/gui/creator/__init__.py
tomogui/gui/datasource/ElementSelector.py
tomogui/gui/datasource/QDataSourceBaseWidget.py
tomogui/gui/datasource/QDataSourceFluoWidget.py
tomogui/gui/datasource/QDataSourceTxWidget.py
tomogui/gui/datasource/QDataSourceWidget.py
tomogui/gui/datasource/QMessageGroupFiles.py
tomogui/gui/datasource/__init__.py
tomogui/gui/datasource/setup.py
tomogui/gui/datasource/tomoguiFileTypeCB.py
tomogui/gui/datasource/sinofileselector/QSinoFileFluoSelector.py
tomogui/gui/datasource/sinofileselector/QSinoFileSelectorBase.py
tomogui/gui/datasource/sinofileselector/QSinoFileTxSelector.py
tomogui/gui/datasource/sinofileselector/SinoFileBrowser.py
tomogui/gui/datasource/sinofileselector/__init__.py
tomogui/gui/datasource/sinograminfo/FluorescenceSinogramInfo.py
tomogui/gui/datasource/sinograminfo/TxSinogramInfo.py
tomogui/gui/datasource/sinograminfo/__init__.py
tomogui/gui/materials/MaterialEditor.py
tomogui/gui/materials/MaterialsFileDialog.py
tomogui/gui/materials/QSampleComposition.py
tomogui/gui/materials/__init__.py
tomogui/gui/normalization/NormWidget.py
tomogui/gui/normalization/QCenteringWidget.py
tomogui/gui/normalization/QRotationCenterWidget.py
tomogui/gui/normalization/__init__.py
tomogui/gui/reconsparam/DetectorSetup.py
tomogui/gui/reconsparam/OpenCLPlatformSelector.py
tomogui/gui/reconsparam/ReconsParamWidget.py
tomogui-0.2.0.dist-info/DESCRIPTION.rst
tomogui-0.2.0.dist-info/METADATA
tomogui-0.2.0.dist-info/RECORD
tomogui-0.2.0.dist-info/WHEEL
tomogui-0.2.0.dist-info/entry_points.txt
tomogui-0.2.0.dist-info/metadata.json
tomogui-0.2.0.dist-info/top_level.txt
